<?xml version="1.0" encoding="UTF-8"?>
<skinset name="Base">
    <imagelist category="anotheroneofpartyinfo_imgs">
		<image name="aop_spray_large_s" file="\skin\large_s.tga" imgrect="0 0 20 20"/>
		<image name="aop_spray_small_s" file="\skin\small_s.tga" imgrect="0 0 10 10"/>
		<image name="aop_spray_large_bs" file="\skin\large_bs.tga" imgrect="0 0 20 20"/>
		<image name="aop_spray_small_bs" file="\skin\small_bs.tga" imgrect="0 0 10 10"/>
		<image name="aop_spray_vsmall_bar" file="\skin\vsmall_bar.tga" imgrect="0 0 10 10"/>
		<image name="aop_spray_small_bar" file="\skin\small_bar.tga" imgrect="0 0 10 10"/>
		<image name="aop_spray_large_bar" file="\skin\large_bar.tga" imgrect="0 0 10 10"/>
		<image name="aop_spray_dia" file="\skin\brush_dia.tga" imgrect="0 0 40 40"/>
		<image name="aop_spray_triangle" file="\skin\brush_triangle.tga" imgrect="0 0 40 40"/>
		
	</imagelist>
</skinset>